MachineLearningForNaturalLanguageProcessingLectureNotesColumbiaE6998/README.md
MachineLearningForNaturalLanguageProcessingLectureNotesColumbiaE6998/__init__.py
MachineLearningForNaturalLanguageProcessingLectureNotesColumbiaE6998/__main__.py
MachineLearningForNaturalLanguageProcessingLectureNotesColumbiaE6998/file.pdf
MachineLearningForNaturalLanguageProcessingLectureNotesColumbiaE6998/index.html
machine_learning_for_natural_language_processing_lecture_notes_columbia_e6998-2024.3.2.0.dist-info/METADATA
machine_learning_for_natural_language_processing_lecture_notes_columbia_e6998-2024.3.2.0.dist-info/WHEEL
machine_learning_for_natural_language_processing_lecture_notes_columbia_e6998-2024.3.2.0.dist-info/entry_points.txt
machine_learning_for_natural_language_processing_lecture_notes_columbia_e6998-2024.3.2.0.dist-info/top_level.txt
machine_learning_for_natural_language_processing_lecture_notes_columbia_e6998-2024.3.2.0.dist-info/RECORD
